pandas_processors/__init__.py
pandas_processors/_utils.py
pandas_processors/create.py
pandas_processors/impute.py
pandas_processors/normalize.py
pandas_processors-0.1.3.dist-info/METADATA
pandas_processors-0.1.3.dist-info/WHEEL
pandas_processors-0.1.3.dist-info/RECORD
