Metadata-Version: 2.4
Name: pandas-processors
Version: 0.1.3
Summary: Add your description here
Requires-Python: >=3.11
Requires-Dist: pandas>=2.3.0
Requires-Dist: scikit-learn>=1.7.0
Requires-Dist: scipy>=1.15.3
